minimal_code/__init__.py
minimal_code/converter.py
minimal_code/copy.py
minimal_code/create.py
minimal_code/imports.py
minimal_code/rename.py
minimal_code/tts.py
minimal_code-1.2.0.dist-info/LICENSE
minimal_code-1.2.0.dist-info/METADATA
minimal_code-1.2.0.dist-info/WHEEL
minimal_code-1.2.0.dist-info/top_level.txt
minimal_code-1.2.0.dist-info/RECORD
