Metadata-Version: 2.1
Name: minimal-code
Version: 1.2.0
Summary: Collection of functions intended to simplify and automate specific tasks.
Home-page: https://github.com/kenf1/minimal_code
Author: KF
Author-email: kenfv1@outlook.com
Classifier: Programming Language :: Python :: 3
Classifier: License :: OSI Approved :: GNU General Public License v3 (GPLv3)
Classifier: Operating System :: OS Independent
Requires-Python: >=3.8
License-File: LICENSE
